wickedhot/__init__.py
wickedhot/form_generator.py
wickedhot/html_form.py
wickedhot/one_hot_encode.py
wickedhot/one_hot_encoder.py
wickedhot/res_sample.py
wickedhot/transform_stream.py
wickedhot/templates/__init__.py
wickedhot/templates/alpaca_example.json
wickedhot/templates/alpaca_form.html
wickedhot/templates/alpaca_header.html
wickedhot/templates/alpaca_index.html
wickedhot-0.2.6.dist-info/LICENSE.txt
wickedhot-0.2.6.dist-info/METADATA
wickedhot-0.2.6.dist-info/WHEEL
wickedhot-0.2.6.dist-info/top_level.txt
wickedhot-0.2.6.dist-info/RECORD
