Metadata-Version: 2.1
Name: wickedhot
Version: 0.2.6
Summary: Wicked easy one-hot-encoding in pure python with (mostly) no dependencies
Home-page: https://github.com/dave31415/wickedhot
Author: David Johnston
Author-email: dave31415@gmail.com
License: MIT
Download-URL: https://pypi.org/project/wickedhot/
Keywords: one-hot encoding,machine learning
Platform: UNKNOWN
License-File: LICENSE.txt
